Metadata-Version: 1.0
Name: python-icinga2api
Version: 0.3
Summary: python icinga2 api 
Home-page: https://github.com/tobiasvdk/python-icinga2api
Author: fmnisme, Tobias von der Krone
Author-email: fmnisme@gmail.com, tobias@vonderkrone.info
License: BSD
Platform: UNKNOWN
